confluenpy/__init__.py
confluenpy/content.py
confluenpy/markdown.py
confluenpy-0.1.23.dist-info/LICENSE
confluenpy-0.1.23.dist-info/METADATA
confluenpy-0.1.23.dist-info/WHEEL
confluenpy-0.1.23.dist-info/RECORD
