Metadata-Version: 2.3
Name: confluenpy
Version: 0.1.23
Summary: 
Author: Matteo Giani
Author-email: matteo.giani.87@gmail.com
Requires-Python: >=3.9,<4.0
Classifier: Programming Language :: Python :: 3
Classifier: Programming Language :: Python :: 3.9
Classifier: Programming Language :: Python :: 3.10
Classifier: Programming Language :: Python :: 3.11
Classifier: Programming Language :: Python :: 3.12
Classifier: Programming Language :: Python :: 3.13
Requires-Dist: atlassian-python-api (>=3.41.9,<4.0.0)
Requires-Dist: pytest-mock (>=3.12.0,<4.0.0)
Requires-Dist: validators (>=0.22.0,<0.23.0)
